plan/__init__.py
plan/_compat.py
plan/commands.py
plan/core.py
plan/exceptions.py
plan/job.py
plan/output.py
plan/utils.py
plan/testsuite/__init__.py
plan/testsuite/commands.py
plan/testsuite/core.py
plan/testsuite/job.py
plan/testsuite/output.py
plan-0.5.dist-info/DESCRIPTION.rst
plan-0.5.dist-info/entry_points.txt
plan-0.5.dist-info/METADATA
plan-0.5.dist-info/metadata.json
plan-0.5.dist-info/RECORD
plan-0.5.dist-info/top_level.txt
plan-0.5.dist-info/WHEEL
