Metadata-Version: 1.1
Name: plan
Version: 0.5
Summary: A Python package for writing and deploying cron jobs with a clear and beautiful syntax.
Home-page: https://github.com/fengsp/plan
Author: Shipeng Feng
Author-email: fsp261@gmail.com
License: BSD
Platform: UNKNOWN
Classifier: Development Status :: 5 - Production/Stable
Classifier: Intended Audience :: Developers
Classifier: License :: OSI Approved :: BSD License
Classifier: Programming Language :: Python
Classifier: Programming Language :: Python :: 2.6
Classifier: Programming Language :: Python :: 2.7
Classifier: Programming Language :: Python :: 3
Classifier: Programming Language :: Python :: 3.3
Classifier: Programming Language :: Python :: 3.4
